ai_graph/__init__.py
ai_graph/pipeline/__init__.py
ai_graph/pipeline/base.py
ai_graph/step/__init__.py
ai_graph/step/base.py
ai_graph/step/foreach.py
ai_graph/step/video/__init__.py
ai_graph/step/video/basic.py
ai_graph-0.0.5.dist-info/METADATA
ai_graph-0.0.5.dist-info/WHEEL
ai_graph-0.0.5.dist-info/licenses/LICENSE
ai_graph-0.0.5.dist-info/RECORD
