Metadata-Version: 2.4
Name: ai-graph
Version: 0.0.5
Summary: AI Graph framework for building processing pipelines
Project-URL: Homepage, https://github.com/msinamsina/ai-graph
Project-URL: Repository, https://github.com/msinamsina/ai-graph.git
Project-URL: Issues, https://github.com/msinamsina/ai-graph/issues
Author-email: Mohammad Sina Allahkaram <msinamsina@gmail.com>
License:                     GNU GENERAL PUBLIC LICENSE
License-File: LICENSE
Keywords: ai,framework,graph,pipeline,processing
Classifier: Development Status :: 3 - Alpha
Classifier: Intended Audience :: Developers
Classifier: License :: OSI Approved :: GNU General Public License v3 (GPLv3)
Classifier: Operating System :: OS Independent
Classifier: Programming Language :: Python :: 3
Classifier: Programming Language :: Python :: 3.9
Classifier: Programming Language :: Python :: 3.10
Classifier: Programming Language :: Python :: 3.11
Classifier: Programming Language :: Python :: 3.12
Classifier: Topic :: Scientific/Engineering :: Artificial Intelligence
Classifier: Topic :: Software Development :: Libraries :: Application Frameworks
Requires-Python: >=3.9
Requires-Dist: opencv-python-headless
Requires-Dist: tqdm>=4.64.0
